setup.py
messangerS.egg-info/PKG-INFO
messangerS.egg-info/SOURCES.txt
messangerS.egg-info/dependency_links.txt
messangerS.egg-info/requires.txt
messangerS.egg-info/top_level.txt
server/__init__.py
server/server.py
server/common/__init__.py
server/common/deskriptors.py
server/common/errors.py
server/common/my_decorators.py
server/common/my_metaclasses.py
server/common/utils.py
server/common/variables.py
server/my_tests/__init__.py
server/my_tests/my_test_server.py
server/server/__init__.py
server/server/add_user.py
server/server/config_window.py
server/server/core.py
server/server/db_server.py
server/server/main_window.py
server/server/remove_user.py
server/server/stat_window.py