Metadata-Version: 1.0
Name: messangerS
Version: 0.0.1
Summary: messangerS
Home-page: UNKNOWN
Author: GalAR
Author-email: galina_87@mail.ru
License: UNKNOWN
Platform: UNKNOWN
